{
  "metric": "망간 가격 MoM",
  "unit": "%",
  "source": "Battery_Weekly_2026.4.27.pdf",
  "extracted_at": "2026-05-03T02:48:48",
  "data": [
    {
      "date": "2017-01-01",
      "value": 0.561
    },
    {
      "date": "2017-01-30",
      "value": 11.248
    },
    {
      "date": "2017-03-01",
      "value": 9.179
    },
    {
      "date": "2017-03-31",
      "value": 0.216
    },
    {
      "date": "2017-04-28",
      "value": -5.559
    },
    {
      "date": "2017-05-28",
      "value": -11.075
    },
    {
      "date": "2017-06-27",
      "value": -13.919
    },
    {
      "date": "2017-07-27",
      "value": -2.887
    },
    {
      "date": "2017-08-24",
      "value": -3.232
    },
    {
      "date": "2017-09-24",
      "value": -3.49
    },
    {
      "date": "2017-10-24",
      "value": -4.266
    },
    {
      "date": "2017-11-23",
      "value": -1.422
    },
    {
      "date": "2017-12-21",
      "value": 2.801
    },
    {
      "date": "2018-01-20",
      "value": -0.474
    },
    {
      "date": "2018-02-19",
      "value": -8.834
    },
    {
      "date": "2018-03-21",
      "value": 11.679
    },
    {
      "date": "2018-04-18",
      "value": 4.698
    },
    {
      "date": "2018-05-19",
      "value": -2.973
    },
    {
      "date": "2018-06-18",
      "value": -2.025
    },
    {
      "date": "2018-07-18",
      "value": -1.077
    },
    {
      "date": "2018-08-15",
      "value": -9.696
    },
    {
      "date": "2018-09-14",
      "value": -5.559
    },
    {
      "date": "2018-10-14",
      "value": 1.336
    },
    {
      "date": "2018-11-13",
      "value": -3.921
    },
    {
      "date": "2018-12-11",
      "value": -2.197
    },
    {
      "date": "2019-01-11",
      "value": -4.438
    },
    {
      "date": "2019-02-10",
      "value": -4.18
    },
    {
      "date": "2019-03-12",
      "value": -4.18
    },
    {
      "date": "2019-04-09",
      "value": -8.144
    },
    {
      "date": "2019-05-09",
      "value": -4.18
    },
    {
      "date": "2019-06-08",
      "value": -0.56
    },
    {
      "date": "2019-07-08",
      "value": -2.887
    },
    {
      "date": "2019-08-05",
      "value": -5.817
    },
    {
      "date": "2019-09-05",
      "value": -4.697
    },
    {
      "date": "2019-10-05",
      "value": 0.302
    },
    {
      "date": "2019-11-04",
      "value": -5.903
    },
    {
      "date": "2019-12-02",
      "value": -5.731
    },
    {
      "date": "2020-01-01",
      "value": -5.645
    },
    {
      "date": "2020-01-31",
      "value": -9.61
    },
    {
      "date": "2020-03-01",
      "value": -6.076
    },
    {
      "date": "2020-03-29",
      "value": 1.681
    },
    {
      "date": "2020-04-29",
      "value": -1.422
    },
    {
      "date": "2020-05-29",
      "value": -8.403
    },
    {
      "date": "2020-06-28",
      "value": 7.542
    },
    {
      "date": "2020-07-26",
      "value": -0.991
    },
    {
      "date": "2020-08-25",
      "value": -7.11
    },
    {
      "date": "2020-09-24",
      "value": -11.247
    },
    {
      "date": "2020-10-24",
      "value": -3.145
    },
    {
      "date": "2020-11-21",
      "value": -0.301
    },
    {
      "date": "2020-12-21",
      "value": -1.766
    },
    {
      "date": "2021-01-21",
      "value": -2.973
    },
    {
      "date": "2021-02-20",
      "value": 1.595
    },
    {
      "date": "2021-03-20",
      "value": 12.11
    },
    {
      "date": "2021-04-19",
      "value": -0.474
    },
    {
      "date": "2021-05-19",
      "value": -1.766
    },
    {
      "date": "2021-06-18",
      "value": -8.834
    },
    {
      "date": "2021-07-16",
      "value": -0.905
    },
    {
      "date": "2021-08-16",
      "value": 4.094
    },
    {
      "date": "2021-09-15",
      "value": -1.594
    },
    {
      "date": "2021-10-15",
      "value": 3.146
    },
    {
      "date": "2021-11-12",
      "value": 18.66
    },
    {
      "date": "2021-12-12",
      "value": 29.089
    },
    {
      "date": "2022-01-11",
      "value": -17.453
    },
    {
      "date": "2022-02-10",
      "value": -24.52
    },
    {
      "date": "2022-03-10",
      "value": -1.508
    },
    {
      "date": "2022-04-10",
      "value": -0.301
    },
    {
      "date": "2022-05-10",
      "value": 0.043
    },
    {
      "date": "2022-06-09",
      "value": -0.56
    },
    {
      "date": "2022-07-07",
      "value": -6.765
    },
    {
      "date": "2022-08-06",
      "value": -9.092
    },
    {
      "date": "2022-09-05",
      "value": -7.627
    },
    {
      "date": "2022-10-05",
      "value": -9.092
    },
    {
      "date": "2022-11-02",
      "value": -5.817
    },
    {
      "date": "2022-12-02",
      "value": -2.887
    },
    {
      "date": "2023-01-02",
      "value": -1.853
    },
    {
      "date": "2023-02-01",
      "value": 0.733
    },
    {
      "date": "2023-03-01",
      "value": -0.56
    },
    {
      "date": "2023-03-31",
      "value": -1.594
    },
    {
      "date": "2023-04-30",
      "value": -5.645
    },
    {
      "date": "2023-05-30",
      "value": -10.04
    },
    {
      "date": "2023-06-27",
      "value": -8.317
    },
    {
      "date": "2023-07-27",
      "value": -8.144
    },
    {
      "date": "2023-08-27",
      "value": -4.266
    },
    {
      "date": "2023-09-26",
      "value": -2.284
    },
    {
      "date": "2023-10-24",
      "value": -3.145
    },
    {
      "date": "2023-11-23",
      "value": -1.853
    },
    {
      "date": "2023-12-23",
      "value": -6.076
    },
    {
      "date": "2024-01-22",
      "value": -4.438
    },
    {
      "date": "2024-02-19",
      "value": -2.111
    },
    {
      "date": "2024-03-20",
      "value": -2.887
    },
    {
      "date": "2024-04-20",
      "value": -3.404
    },
    {
      "date": "2024-05-20",
      "value": -5.99
    },
    {
      "date": "2024-06-17",
      "value": 19.005
    },
    {
      "date": "2024-07-17",
      "value": 5.129
    },
    {
      "date": "2024-08-16",
      "value": -10.989
    },
    {
      "date": "2024-09-15",
      "value": -7.627
    },
    {
      "date": "2024-10-13",
      "value": -5.473
    },
    {
      "date": "2024-11-12",
      "value": -6.507
    },
    {
      "date": "2024-12-13",
      "value": -3.749
    },
    {
      "date": "2025-01-12",
      "value": -3.835
    },
    {
      "date": "2025-02-09",
      "value": -4.18
    },
    {
      "date": "2025-03-11",
      "value": -1.163
    },
    {
      "date": "2025-04-10",
      "value": -4.869
    },
    {
      "date": "2025-05-10",
      "value": -5.817
    },
    {
      "date": "2025-06-07",
      "value": -2.715
    },
    {
      "date": "2025-07-07",
      "value": -4.524
    },
    {
      "date": "2025-08-07",
      "value": -4.18
    },
    {
      "date": "2025-09-06",
      "value": -1.68
    },
    {
      "date": "2025-10-04",
      "value": -2.37
    },
    {
      "date": "2025-11-03",
      "value": -2.715
    },
    {
      "date": "2025-12-03",
      "value": -2.628
    },
    {
      "date": "2026-01-02",
      "value": -1.766
    },
    {
      "date": "2026-01-30",
      "value": -0.818
    },
    {
      "date": "2026-03-01",
      "value": -1.853
    },
    {
      "date": "2026-04-01",
      "value": -1.594
    }
  ],
  "verified": true,
  "needs_review": false,
  "verification": {
    "drift": "ok",
    "matched_label": "도표 66. 망간 월별 평균 가격 추이",
    "dy": 0.0,
    "dx": 0.0
  }
}