{
  "metric": "SK하이닉스 12MF PBR 밴드 - 수정주가",
  "unit": "원",
  "label": "수정주가",
  "source": "Weekly_Roko_260427.pdf",
  "extracted_at": "2026-05-02T06:16:16",
  "data": [
    {
      "date": "2016-02-29",
      "value": 0
    },
    {
      "date": "2016-03-30",
      "value": 0
    },
    {
      "date": "2016-05-01",
      "value": 0
    },
    {
      "date": "2016-05-30",
      "value": 0
    },
    {
      "date": "2016-06-29",
      "value": 0
    },
    {
      "date": "2016-07-29",
      "value": 0
    },
    {
      "date": "2016-08-27",
      "value": 0
    },
    {
      "date": "2016-09-28",
      "value": 0
    },
    {
      "date": "2016-10-28",
      "value": 0
    },
    {
      "date": "2016-11-27",
      "value": 0
    },
    {
      "date": "2016-12-26",
      "value": 0
    },
    {
      "date": "2017-01-25",
      "value": 0
    },
    {
      "date": "2017-02-26",
      "value": 0
    },
    {
      "date": "2017-03-28",
      "value": 0
    },
    {
      "date": "2017-04-26",
      "value": 0
    },
    {
      "date": "2017-05-26",
      "value": 0
    },
    {
      "date": "2017-06-27",
      "value": 0
    },
    {
      "date": "2017-07-26",
      "value": 8790.0
    },
    {
      "date": "2017-08-25",
      "value": 8790.0
    },
    {
      "date": "2017-09-24",
      "value": 10653.0
    },
    {
      "date": "2017-10-23",
      "value": 25551.0
    },
    {
      "date": "2017-11-24",
      "value": 23689.0
    },
    {
      "date": "2017-12-24",
      "value": 18102.0
    },
    {
      "date": "2018-01-23",
      "value": 18102.0
    },
    {
      "date": "2018-02-21",
      "value": 16239.0
    },
    {
      "date": "2018-03-23",
      "value": 18102.0
    },
    {
      "date": "2018-04-24",
      "value": 23689.0
    },
    {
      "date": "2018-05-24",
      "value": 27413.0
    },
    {
      "date": "2018-06-22",
      "value": 34863.0
    },
    {
      "date": "2018-07-22",
      "value": 27413.0
    },
    {
      "date": "2018-08-20",
      "value": 29276.0
    },
    {
      "date": "2018-09-21",
      "value": 25551.0
    },
    {
      "date": "2018-10-21",
      "value": 14377.0
    },
    {
      "date": "2018-11-20",
      "value": 10653.0
    },
    {
      "date": "2018-12-19",
      "value": 12515.0
    },
    {
      "date": "2019-01-20",
      "value": 3203.0
    },
    {
      "date": "2019-02-19",
      "value": 16239.0
    },
    {
      "date": "2019-03-21",
      "value": 12515.0
    },
    {
      "date": "2019-04-19",
      "value": 16239.0
    },
    {
      "date": "2019-05-19",
      "value": 21826.0
    },
    {
      "date": "2019-06-20",
      "value": 6928.0
    },
    {
      "date": "2019-07-20",
      "value": 10653.0
    },
    {
      "date": "2019-08-18",
      "value": 18102.0
    },
    {
      "date": "2019-09-17",
      "value": 19964.0
    },
    {
      "date": "2019-10-17",
      "value": 23689.0
    },
    {
      "date": "2019-11-18",
      "value": 23689.0
    },
    {
      "date": "2019-12-17",
      "value": 23689.0
    },
    {
      "date": "2020-01-16",
      "value": 36725.0
    },
    {
      "date": "2020-02-14",
      "value": 34863.0
    },
    {
      "date": "2020-03-15",
      "value": 29276.0
    },
    {
      "date": "2020-04-16",
      "value": 25551.0
    },
    {
      "date": "2020-05-16",
      "value": 25551.0
    },
    {
      "date": "2020-06-14",
      "value": 23689.0
    },
    {
      "date": "2020-07-14",
      "value": 27413.0
    },
    {
      "date": "2020-08-15",
      "value": 25551.0
    },
    {
      "date": "2020-09-14",
      "value": 18102.0
    },
    {
      "date": "2020-10-13",
      "value": 25551.0
    },
    {
      "date": "2020-11-12",
      "value": 21826.0
    },
    {
      "date": "2020-12-12",
      "value": 40449.0
    },
    {
      "date": "2021-01-13",
      "value": 60935.0
    },
    {
      "date": "2021-02-11",
      "value": 64659.0
    },
    {
      "date": "2021-03-13",
      "value": 83283.0
    },
    {
      "date": "2021-04-11",
      "value": 73971.0
    },
    {
      "date": "2021-05-11",
      "value": 70246.0
    },
    {
      "date": "2021-06-12",
      "value": 68384.0
    },
    {
      "date": "2021-07-12",
      "value": 70246.0
    },
    {
      "date": "2021-08-10",
      "value": 55348.0
    },
    {
      "date": "2021-09-09",
      "value": 47899.0
    },
    {
      "date": "2021-10-09",
      "value": 44174.0
    },
    {
      "date": "2021-11-10",
      "value": 44174.0
    },
    {
      "date": "2021-12-09",
      "value": 55348.0
    },
    {
      "date": "2022-01-08",
      "value": 72109.0
    },
    {
      "date": "2022-02-07",
      "value": 62797.0
    },
    {
      "date": "2022-03-11",
      "value": 64659.0
    },
    {
      "date": "2022-04-09",
      "value": 60935.0
    },
    {
      "date": "2022-05-09",
      "value": 55348.0
    },
    {
      "date": "2022-06-07",
      "value": 49761.0
    },
    {
      "date": "2022-07-07",
      "value": 33000.0
    },
    {
      "date": "2022-08-08",
      "value": 40449.0
    },
    {
      "date": "2022-09-07",
      "value": 36725.0
    },
    {
      "date": "2022-10-06",
      "value": 25551.0
    },
    {
      "date": "2022-11-05",
      "value": 25551.0
    },
    {
      "date": "2022-12-05",
      "value": 27413.0
    },
    {
      "date": "2023-01-06",
      "value": 16239.0
    },
    {
      "date": "2023-02-04",
      "value": 31138.0
    },
    {
      "date": "2023-03-06",
      "value": 31138.0
    },
    {
      "date": "2023-04-05",
      "value": 31138.0
    },
    {
      "date": "2023-05-04",
      "value": 31138.0
    },
    {
      "date": "2023-06-05",
      "value": 49761.0
    },
    {
      "date": "2023-07-05",
      "value": 57210.0
    },
    {
      "date": "2023-08-03",
      "value": 64659.0
    },
    {
      "date": "2023-09-02",
      "value": 64659.0
    },
    {
      "date": "2023-10-02",
      "value": 57210.0
    },
    {
      "date": "2023-11-03",
      "value": 59073.0
    },
    {
      "date": "2023-12-02",
      "value": 75833.0
    },
    {
      "date": "2024-01-01",
      "value": 83283.0
    },
    {
      "date": "2024-01-31",
      "value": 75833.0
    },
    {
      "date": "2024-03-03",
      "value": 98181.0
    },
    {
      "date": "2024-04-01",
      "value": 124253.0
    },
    {
      "date": "2024-05-01",
      "value": 116804.0
    },
    {
      "date": "2024-05-31",
      "value": 131703.0
    },
    {
      "date": "2024-06-29",
      "value": 178260.0
    },
    {
      "date": "2024-07-31",
      "value": 137290.0
    },
    {
      "date": "2024-08-30",
      "value": 114942.0
    },
    {
      "date": "2024-09-29",
      "value": 116804.0
    },
    {
      "date": "2024-10-28",
      "value": 127978.0
    },
    {
      "date": "2024-11-27",
      "value": 101906.0
    },
    {
      "date": "2024-12-29",
      "value": 116804.0
    },
    {
      "date": "2025-01-27",
      "value": 141014.0
    },
    {
      "date": "2025-02-26",
      "value": 131703.0
    },
    {
      "date": "2025-03-28",
      "value": 133565.0
    },
    {
      "date": "2025-04-26",
      "value": 118666.0
    },
    {
      "date": "2025-05-28",
      "value": 146601.0
    },
    {
      "date": "2025-06-27",
      "value": 234130.0
    },
    {
      "date": "2025-07-27",
      "value": 215506.0
    },
    {
      "date": "2025-08-25",
      "value": 211782.0
    },
    {
      "date": "2025-09-26",
      "value": 289999.0
    },
    {
      "date": "2025-10-26",
      "value": 500440.0
    },
    {
      "date": "2025-11-25",
      "value": 472505.0
    },
    {
      "date": "2025-12-24",
      "value": 591693.0
    },
    {
      "date": "2026-01-23",
      "value": 850554.0
    },
    {
      "date": "2026-02-24",
      "value": 1001401.0
    },
    {
      "date": "2026-03-25",
      "value": 748127.0
    },
    {
      "date": "2026-04-24",
      "value": 1163422.0
    }
  ]
}